hatch_javascript/__init__.py
hatch_javascript/tests/test_all.py
hatch_javascript-0.1.0.dist-info/METADATA
hatch_javascript-0.1.0.dist-info/WHEEL
hatch_javascript-0.1.0.dist-info/licenses/LICENSE
hatch_javascript-0.1.0.dist-info/RECORD
